alastria_identity/examples/alastria_contract_config_generation.py
alastria_identity/services/__init__.py
alastria_identity/services/config_builder.py
alastria_identity/services/contracts.py
alastria_identity/services/credential_registry.py
alastria_identity/services/identity.py
alastria_identity/services/identity_manager.py
alastria_identity/services/parsers.py
alastria_identity/services/presentation_registry.py
alastria_identity/services/public_key.py
alastria_identity/services/tokens.py
alastria_identity/tests/test_credential_registry.py
alastria_identity/tests/test_identity_manager.py
alastria_identity/tests/test_parsers.py
alastria_identity/tests/test_presentation_registry.py
alastria_identity/tests/test_public_key.py
alastria_identity/tests/test_tokens.py
alastria_identity/types/__init__.py
alastria_identity/types/alastria_identity_creation.py
alastria_identity/types/alastria_session.py
alastria_identity/types/alastria_token.py
alastria_identity/types/credential.py
alastria_identity/types/entity.py
alastria_identity/types/presentation.py
alastria_identity/types/presentation_request.py
alastria_identity/types/transaction.py
alastria_identity-0.3.0.dist-info/LICENSE
alastria_identity-0.3.0.dist-info/WHEEL
alastria_identity-0.3.0.dist-info/METADATA
alastria_identity-0.3.0.dist-info/RECORD
