Metadata-Version: 2.1
Name: alastria-identity
Version: 0.3.0
Summary: 
Home-page: https://github.com/Wealize/alastria-identity-lib-py
License: MIT
Author: Javier Aguirre
Author-email: javi@wealize.digital
Requires-Python: >=3.8,<4.0
Classifier: License :: OSI Approved :: MIT License
Classifier: Programming Language :: Python :: 3
Classifier: Programming Language :: Python :: 3.8
Classifier: Programming Language :: Python :: 3.9
Requires-Dist: ecdsa (>=0.16.1,<0.17.0)
Requires-Dist: eth_abi (>=2.1.1,<3.0.0)
Requires-Dist: jwcrypto (>=0.8,<0.9)
Requires-Dist: mock (>=4.0.2,<5.0.0)
Requires-Dist: pytest (>=6.1.1,<7.0.0)
Requires-Dist: requests (>=2.24.0,<3.0.0)
Requires-Dist: web3 (>=5.13.0,<6.0.0)
Project-URL: Repository, https://github.com/Wealize/alastria-identity-lib-py
